openlab/__init__.py
openlab/account.py
openlab/credentials.py
openlab/exceptions.py
openlab/logger.py
openlab/login.py
openlab/piController.py
openlab/results.py
openlab/setpoints.py
openlab-2.5.7.dist-info/METADATA
openlab-2.5.7.dist-info/WHEEL
openlab-2.5.7.dist-info/top_level.txt
openlab-2.5.7.dist-info/RECORD
