Metadata-Version: 2.1
Name: openlab
Version: 2.5.7
Summary: A python client for OpenLab Drilling.
Home-page: https://live.openlab.app
Author: NORCE
Author-email: andrew.holsaeter@norceresearch.no
License: NORCE COPYRIGHT: Do not distribute without approval by NORCE
Classifier: Development Status :: 4 - Beta
Classifier: Programming Language :: Python :: 3.6
Classifier: Intended Audience :: Developers
Requires-Dist: oauthlib >=2.0.7
Requires-Dist: requests >=2.20.0
Requires-Dist: requests-oauthlib >=0.4
Requires-Dist: validators
Requires-Dist: datetime
Requires-Dist: matplotlib
Requires-Dist: uuid
Requires-Dist: keyring
Requires-Dist: numpy
Requires-Dist: outdated >=0.2.0
